gooder.py
gooder-0.3.2.dist-info/COPYING.lesser
gooder-0.3.2.dist-info/COPYING
gooder-0.3.2.dist-info/WHEEL
gooder-0.3.2.dist-info/METADATA
gooder-0.3.2.dist-info/RECORD
